{
    "file": "wire\/modules\/Process\/ProcessLogin\/ProcessLogin.module",
    "textdomain": "wire--modules--process--processlogin--processlogin-module",
    "translations": {
        "5048eab3b6b17142d965cf9d43f6e460": {
            "text": "Sie sind eingeloggt."
        },
        "a0bfb8e59e6c13fc8d990781f77694fe": {
            "text": "Fortsetzen"
        },
        "847549ae30061a6767a4b17c6fb4f53c": {
            "text": "Erfolgreich eingeloggt"
        },
        "48649d8c2d04aa439d10bc45eaba8f75": {
            "text": "Login fehlgeschlagen"
        },
        "646d9e77201093e05380ead006df9975": {
            "text": "Sicherheitswarnung: %s existiert und sollte so schnell wie m\u00f6glich gel\u00f6scht werden."
        },
        "f6039d44b29456b20f8f373155ae4973": {
            "text": "Benutzername"
        },
        "dc647eb65e6711e155375218212b3964": {
            "text": "Passwort"
        },
        "99dea78007133396a7b8ed70578ac6ae": {
            "text": "Einloggen"
        },
        "01a569ddc6cf67ddec2a683f0a5f5956": {
            "text": "Passwort vergessen?"
        },
        "0d5dfb1efbd4144f5e7c8d80df1d09f1": {
            "text": "Sie haben sich ausgeloggt"
        },
        "d837cc5a72556c5e2abf4b9fe10ddef8": {
            "text": "Login"
        },
        "4c429484c06b2d2901b3a582f300af56": {
            "text": "Achtung, in Ihrer \/site\/config.php sind Dateiberechtigungen definiert, welche f\u00fcr viele Umgebungen zu locker sind:"
        },
        "00796cc045b871fe7b2867edef6aaaf7": {
            "text": "Um diese Warnung zu unterdr\u00fccken, setzen Sie in ihrer \/site\/config.php Datei die Einstellung $config->chmodWarn = false;"
        },
        "748befe7a5d432caba8b6cadc4076e92": {
            "text": "Lesen Sie \"Absichern von Dateiberechtigungen\" f\u00fcr weitere Details"
        },
        "d5877d284caca4c9b4d55adb8e6e758c": {
            "text": "Zum Beispiel k\u00f6nnte die Gebietsschema-Einstellung f\u00fcr US-Englisch sein: %s"
        },
        "1860fb17b107cbb39cf6bbfa61130803": {
            "text": "Profil bearbeiten"
        },
        "8b10281154afa6312e3e8448c14f7134": {
            "text": "Zwei-Faktor-Authentifizierung"
        },
        "c32dc189adbf7de6a1277780634d1a75": {
            "text": "Die folgenden Tfa-Module wurden gefunden:"
        },
        "f00ee62461e9cc7a824e71feff114251": {
            "text": "Empfehlen Sie nachdr\u00fccklich eine Zwei-Faktor-Authentifizierung f\u00fcr diese Rollen"
        },
        "ab848ea82288648eb2aabe4e9e2f4dc6": {
            "text": "Nach der Anmeldung beim Admin-Backend fordert ProcessWire die Benutzer in den hier ausgew\u00e4hlten Rollen auf, die Zwei-Faktor-Authentifizierung f\u00fcr ihre Konten zu verwenden."
        },
        "ab77fff843383131e8f774ba78654a91": {
            "text": "Um dies zu konfigurieren, m\u00fcssen Sie zuerst ein oder mehrere Tfa-Module installieren und dann hierher zur\u00fcckkehren."
        },
        "aef111cc10b28b4cf297865dbc1253bb": {
            "text": "Tfa-Module im ProcessWire-Modulverzeichnis"
        },
        "60d0f1128804dfd5fa013c3d02c67012": {
            "text": "Ihre aktuelle Gebietsschema-Einstellung ist \"%s\"."
        },
        "9cdeee8e8a463c558dc372434cc5dbb1": {
            "text": "Hinweis: Ihre aktuelle Gebietsschema-Einstellung (locale) funktioniert nicht wie erwartet mit dem UTF-8 Zeichensatz und kann kleinere Probleme verursachen."
        },
        "f8239d6a9013fae244731a805aa50b09": {
            "text": "Bitte \u00fcbersetzen Sie die \"C\" Gebietsschema-Einstellung (locale) f\u00fcr jede Sprache in das richtige Gebietsschema (locale) in %s"
        },
        "7ca79a1980d88028a56fcee7c711685e": {
            "text": "Bitte f\u00fcgt dies zu Ihrer %1$s Datei hinzu (passen Sie \"%2$s\" bei Bedarf an):"
        }
    }
}